{
  "indexes": [
    {
      "collectionGroup": "users",
      "queryScope": "COLLECTION",
      "fields": [
        {
          "fieldPath": "accountStatus",
          "order": "ASCENDING"
        },
        {
          "fieldPath": "role",
          "order": "ASCENDING"
        },
        {
          "fieldPath": "createdAt",
          "order": "DESCENDING"
        }
      ]
    },
    {
      "collectionGroup": "practitioner_applications",
      "queryScope": "COLLECTION",
      "fields": [
        {
          "fieldPath": "status",
          "order": "ASCENDING"
        },
        {
          "fieldPath": "submittedAt",
          "order": "DESCENDING"
        }
      ]
    },
    {
      "collectionGroup": "sessions",
      "queryScope": "COLLECTION",
      "fields": [
        {
          "fieldPath": "patientId",
          "order": "ASCENDING"
        },
        {
          "fieldPath": "sessionNumber",
          "order": "ASCENDING"
        }
      ]
    },
    {
      "collectionGroup": "sessions",
      "queryScope": "COLLECTION",
      "fields": [
        {
          "fieldPath": "patientId",
          "order": "ASCENDING"
        },
        {
          "fieldPath": "sessionNumber",
          "order": "DESCENDING"
        }
      ]
    }
  ],
  "fieldOverrides": [
    {
      "collectionGroup": "sessions",
      "fieldPath": "date",
      "indexes": [
        {
          "order": "ASCENDING",
          "queryScope": "COLLECTION_GROUP"
        },
        {
          "order": "DESCENDING",
          "queryScope": "COLLECTION_GROUP"
        }
      ]
    }
  ]
}
